aces_high_core/__init__.py
aces_high_core/py.typed
aces_high_core/_jsii/__init__.py
aces_high_core/_jsii/aces-high-core@2.3.1.jsii.tgz
aces_high_core-2.3.1.dist-info/LICENSE
aces_high_core-2.3.1.dist-info/METADATA
aces_high_core-2.3.1.dist-info/WHEEL
aces_high_core-2.3.1.dist-info/top_level.txt
aces_high_core-2.3.1.dist-info/RECORD
